sphinxcontrib/__init__.py
sphinxcontrib/excel.py
sphinxcontrib_excel-0.0.1.dist-info/DESCRIPTION.rst
sphinxcontrib_excel-0.0.1.dist-info/METADATA
sphinxcontrib_excel-0.0.1.dist-info/RECORD
sphinxcontrib_excel-0.0.1.dist-info/WHEEL
sphinxcontrib_excel-0.0.1.dist-info/metadata.json
sphinxcontrib_excel-0.0.1.dist-info/top_level.txt
